{
    "soma": {
        "mechanisms": {
            "pas": {
                "0.5": {
                    "e_pas": -60,
                    "g_pas": 0.000033
                }
            },
            "k_ion": {
                "0.5": {
                    "ek": -90
                }
            },
            "na_ion": {
                "0.5": {
                    "ena": 50
                }
            },
            "nat": {
                "0.5": {}
            },
            "kdr": {
                "0.5": {}
            },
            "ka": {
                "0.5": {}
            },
            "km": {
                "0.5": {}
            }
        },
        "geom": {
            "diam": 5641.9,
            "L": 5641.9
        },
        "Ra": 100,
        "cm": 1.4,
        "nseg": 1
    }
}